CHANGELOG.rst
MANIFEST.in
README.rst
firmasat.py
pyproject.toml
setup.cfg
setup.py
firmasatpy.egg-info/PKG-INFO
firmasatpy.egg-info/SOURCES.txt
firmasatpy.egg-info/dependency_links.txt
firmasatpy.egg-info/top_level.txt
test/test_firmasat.py
test/work/A7.xml
test/work/AAA010101AAA201501BN-base.xml
test/work/AAA010101AAA201501CT-base.xml
test/work/AAA010101AAA201501CT_new-signed.xml
test/work/AAA010101AAA201705CT.xml
test/work/AC4_SAT.cer
test/work/CSD_E12345CV_ACP020530MP5.cer
test/work/CSD_E12345CV_ACP020530MP5.key
test/work/ConVolE12345-base.xml
test/work/ConVolE12345-signed2015.xml
test/work/ConVolE12345_new-signed.xml
test/work/Contrasena de Clave Privada.txt
test/work/Ejemplo_Retenciones-base.xml
test/work/V3_2_BadCurp.xml
test/work/archivo_new-pfx.txt
test/work/cfdv33a-signed-tfd.xml
test/work/cfdv40-bad-nover.xml
test/work/cfdv40-badimpuestos.xml
test/work/cfdv40-detallista.xml
test/work/cfdv40-ejemplo-badsign.xml
test/work/cfdv40-ejemplo-missing-tipofactor.xml
test/work/cfdv40-ejemplo-niño-latin1.xml
test/work/cfdv40-ejemplo-niño-noenc.xml
test/work/cfdv40-ejemplo-niño.xml
test/work/cfdv40-ejemplo-nocertnum.xml
test/work/cfdv40-ejemplo-signed-tfd.xml
test/work/cfdv40-ejemplo.xml
test/work/cfdv40-ejemplo_signed.xml
test/work/cfdv40-ejemplo_signed_new_tfd.xml
test/work/cfdv40-iedu-badcurp.xml
test/work/cfdv40-min-signed-nobom.xml
test/work/cfdv40-min-signed-with-BOM.xml
test/work/cfdv40-nomina12-noenc.xml
test/work/cfdv40-nomina12.xml
test/work/cfdv40-nomina12_plus_cert.xml
test/work/cfdv40_new-pluscert.xml
test/work/cfdv40_new-signed-pluscert.xml
test/work/contab-SelloDigitalContElec-signed.xml
test/work/detallista_new-signed.xml
test/work/ejemplo_v32-badsign.xml
test/work/ejemplo_v32-base2015.xml
test/work/ejemplo_v32-signed2015.xml
test/work/ejemplo_v32-tfd2015.xml
test/work/ejemplo_v32.xml
test/work/emisor.cer
test/work/emisor.key
test/work/emisor1024.cer
test/work/emisor1024.key
test/work/emisor_new.key
test/work/emisor_new.pem
test/work/pac.cer
test/work/pac.key
test/work/pac1024.cer
test/work/pac1024.key
test/work/retenciones20-ejemplo.xml