Metadata-Version: 2.4
Name: firmasatpy
Version: 10.70.0
Summary: Python interface to FirmaSAT
Home-page: https://cryptosys.net/firmasat/
Author: David Ireland, DI Management Services Pty Ltd t/a CryptoSys
Project-URL: Homepage, https://cryptosys.net/firmasat/
Project-URL: Issues, https://cryptosys.net/contact/
Platform: Windows
Classifier: Programming Language :: Python :: 3
Requires-Python: >=3.6
Dynamic: home-page
Dynamic: platform
